LICENSE
README.md
setup.py
Hcl.py.egg-info/PKG-INFO
Hcl.py.egg-info/SOURCES.txt
Hcl.py.egg-info/dependency_links.txt
Hcl.py.egg-info/requires.txt
Hcl.py.egg-info/top_level.txt
hcl/__init__.py
hcl/acm.py
hcl/client.py
hcl/settings.py
hcl/socket.py
hcl/subclient.py
hcl/src/__init__.py
hcl/src/debugs.py
hcl/src/didgen.py
hcl/src/exceptions.py
hcl/src/exceptions_v2.py
hcl/src/headers.py
hcl/src/objects.py
hcl/src/voice_header.py