Metadata-Version: 2.1
Name: Hcl.py
Version: 0.8.2
Summary: An api including Amino web and app websocket
Home-page: https://github.com/Oustex/hcl.py
Author: Oustex
Author-email: oustexp@gmail.com
License: Apache V2
Download-URL: https://github.com/Oustex/hcl.py/tarball/master
Project-URL: Source, https://github.com/Oustex/Hcl.py
Keywords: aminoapps,hcl-py,Hydrochloric.py,Hydrochloric-py,Hydrochloric,amino,amino-bot,narvii,api,slimakoi,kapidev,syscall,oustex,AminoBot,botamino,aminobot
Platform: UNKNOWN
Classifier: Programming Language :: Python :: 3
Classifier: License :: OSI Approved :: MIT License
Classifier: Operating System :: OS Independent
License-File: LICENSE
